tusclient.py
tusclient-0.2.1.dist-info/DESCRIPTION.rst
tusclient-0.2.1.dist-info/RECORD
tusclient-0.2.1.dist-info/metadata.json
tusclient-0.2.1.dist-info/WHEEL
tusclient-0.2.1.dist-info/top_level.txt
tusclient-0.2.1.dist-info/METADATA
tusclient-0.2.1.dist-info/pbr.json
