Metadata-Version: 2.0
Name: tusclient
Version: 0.2.1
Summary: python client for tus protocol 1.0.0
Home-page: https://github.com/everydo/tusclient
Author: easydo.cn
Author-email: info@easydo.cn
License: MIT
Keywords: tus client
Platform: UNKNOWN
Classifier: Development Status :: 3 - Alpha
Classifier: Programming Language :: Python :: 2
Classifier: Programming Language :: Python :: 2.7
Classifier: Topic :: Internet :: WWW/HTTP
Classifier: License :: OSI Approved :: MIT License
Requires-Dist: requests
